lensql/__init__.py
lensql/database.py
lensql/server.py
lensql/sql_errors.py
lensql/notebook/__init__.py
lensql/notebook/hook.py
lensql/notebook/run_cell.py
lensql/webui/__init__.py
lensql/webui/chat.py
lensql/webui/html.py
lensql/webui/load_content.py
lensql/webui/style.css
lensql-0.1.8.dist-info/METADATA
lensql-0.1.8.dist-info/WHEEL
lensql-0.1.8.dist-info/RECORD
